flet_route_async/__init__.py
flet_route_async/basket.py
flet_route_async/not_found_view.py
flet_route_async/params.py
flet_route_async/routing.py
flet_route_async-0.2.3.dist-info/LICENSE
flet_route_async-0.2.3.dist-info/METADATA
flet_route_async-0.2.3.dist-info/WHEEL
flet_route_async-0.2.3.dist-info/top_level.txt
flet_route_async-0.2.3.dist-info/RECORD
