Metadata-Version: 2.1
Name: flet-route-async
Version: 0.2.3
Summary: This makes it easy to manage multiple views with dynamic routing.
Home-page: https://github.com/saurabhwadekar/flet_route
Author: Saurabh Wadekar [ INDIA ]
Maintainer: Saurabh Wadekar
Maintainer-email: saurabhwadekar420@gmail.com
License: MIT
Keywords: flet,routing,flet_route,routes,flet app,flet-route,flet simple routing
Requires: flet
Requires: repath
License-File: LICENSE
